{
  "result": true,
  "data": [
    {
      "idBook": "8133",
      "created": "2018-12-27 21:41:17",
      "updated": "2019-01-19 12:13:50",
      "idBookType": "book",
      "idProductsVariations": "8858",
      "title": "\u0623\u062c\u0645\u0644 \u0627\u0644\u062d\u0643\u0627\u064a\u0627\u062a \u0648\u0627\u0644\u0623\u0633\u0627\u0637\u064a\u0631 \u0627\u0644\u0641\u0631\u0639\u0648\u0646\u064a\u0629",
      "titleEn": null,
      "idFileCover": "46438",
      "idFileContent": null,
      "annotation": "\u062c\u0645\u0639\u062a \u0644\u0643 \u0641\u064a \u0647\u0630\u0627 \u0627\u0644\u0643\u062a\u0627\u0628 \u0627\u062c\u0645\u0644 \u0627\u0644\u062d\u0643\u0627\u064a\u0627\u062a \u0648\u0627\u0644\u0623\u0633\u0627\u0637\u064a\u0631 \u0627\u0644\u0641\u0631\u0639\u0648\u0646\u064a\u0629 \u0644\u064a\u0633 \u0641\u0642\u0637 \u0628\u063a\u0631\u0636 \u0627\u0644\u0625\u0645\u062a\u0627\u0639 \u0648\u0644\u0643\u0646 \u0644\u062a\u062a\u0639\u0631\u0641 \u0623\u064a\u0647\u0627 \u0627\u0644\u0642\u0627\u0631\u0626 \u0639\u0644\u064a \u0628\u0639\u0636 \u0645\u0638\u0627\u0647\u0631 \u0627\u0644\u062d\u0636\u0627\u0631\u0629 \u0648\u0627\u0644\u0641\u0643\u0631 \u0648\u0627\u0644\u0639\u0642\u0627\u0626\u062f \u0627\u0644\u0645\u0635\u0631\u064a\u0629 \u0627\u0644\u0642\u062f\u064a\u0645\u0629 \u0648\u0642\u062f \u0635\u063a\u062a\u0647\u0627 \u0644\u0643 \u0628\u0637\u0631\u064a\u0642\u0629 \u0645\u0628\u0633\u0637\u0629 \u0628\u062d\u064a\u062b \u064a\u0645\u0643\u0646 \u0644\u0644\u0643\u0628\u0627\u0631 \u0648\u0627\u0644\u0634\u0628\u0627\u0628 \u0648\u062d\u062a\u0649 \u0627\u0644\u0627\u0637\u0641\u0627\u0644 \u0627\u0644\u0627\u0633\u062a\u0645\u062a\u0627\u0639 \u0628\u0647\u0627 \u0648\u0642\u0631\u0627\u0621\u062a\u0647\u0627.",
      "annotationEn": null,
      "idBookSeries": null,
      "seriesNumber": null,
      "ISBNEbook": null,
      "ISBNEbookLocked": "0",
      "ISBNPrinted": null,
      "ISBNMobi": null,
      "idPublisher": "2062",
      "uid": "240e1e76-0a20-11e9-8801-901b0eed556c",
      "version": "254",
      "idLanguage": "ar",
      "canBeUsedInMinimart": "1",
      "autoCoverPage": null,
      "autoTitlePage": null,
      "autoCopyrightPage": null,
      "originalTitle": null,
      "publishingYear": "2018",
      "idFilePDFCover": null,
      "idPODOption": "11514",
      "printedIn": null,
      "designMode": "1",
      "ebookPublisher": null,
      "idUserExtSales": "11794",
      "sumItunes": null,
      "sumElib": null,
      "sumApp": null,
      "lastExtSalesMailDate": null,
      "idBookUploadAgent": null,
      "publishDate": "2019-01-15 21:27:52",
      "approveDate": "2019-01-19 12:13:50",
      "translitTitle": null,
      "translitAnnotation": null,
      "addUTMCodes": "0",
      "focusBookDate": null,
      "activityRating": "72",
      "deleted": "0",
      "referencePageCount": null,
      "referencePageCountIgnore": "0",
      "chapterCount": "14",
      "wordCount": "5350",
      "rtl": "1",
      "languageName": "Arabic",
      "idUser": "11794",
      "userLogin": "Princessasola55@gmail.com",
      "price": "2.00",
      "VAT": "0.0000",
      "currencyDesignation": "$",
      "priceConverted": "2.000000000",
      "VATConverted": "0.000000000",
      "currencyDesignationConverted": "$",
      "isBought": "0",
      "isFavorite": "0",
      "bwcCurrentPage": null,
      "bwcFontSize": null,
      "isMyBook": "0",
      "extSalesUpdated": "1",
      "adminTitle": "\u0623\u062c\u0645\u0644 \u0627\u0644\u062d\u0643\u0627\u064a\u0627\u062a \u0648\u0627\u0644\u0623\u0633\u0627\u0637\u064a\u0631 \u0627\u0644\u0641\u0631\u0639\u0648\u0646\u064a\u0629 [Princessasola55@gmail.com] {8133}",
      "KBHash": null,
      "mobi": "0",
      "epub": "0",
      "fb2": "0",
      "eNovella": "0",
      "PDF": "0",
      "POD": "0",
      "borrowedLibraryThisMonth": null,
      "borrowedUserThisMonth": null,
      "borrowCount": null,
      "haveLeaseInAnotherLibrary": null,
      "isLibraryUser": null,
      "budgetUsed": null,
      "coverFileData": "{\"idFile\":46438,\"ext\":\"jpg\",\"name\":\"\u0623\u062c\u0645\u0644 \u0627\u0644\u062d\u0643\u0627\u064a\u0627\u062a \u0648\u0627\u0644\u0623\u0633\u0627\u0637\u064a\u0631 \u0627\u0644\u0641\u0631\u0639\u0648\u0646\u064a\u0629\",\"width\":643,\"height\":1009}",
      "bookAuthorsJSON": null,
      "bookGenresJSON": null,
      "booksAccessJSON": null,
      "images": [
        "46438"
      ],
      "bookAuthors": [
        {
          "caption": "\u0647\u0627\u0644\u0647 \u062d\u0633\u0646\u064a \u062d\u0645\u0627\u062f",
          "email": "Princessasola55@gmail.com",
          "firstName": "\u0647\u0627\u0644\u0647",
          "homePage": null,
          "idAuthor": "6492",
          "lastName": "\u062d\u0645\u0627\u062f",
          "middleName": "\u062d\u0633\u0646\u064a",
          "nickname": null
        }
      ],
      "bookGenres": [
        {
          "fb2Name": null,
          "idBook": "8133",
          "idBookGenre": "18209",
          "idGenre": "482",
          "name": "History and civilisations"
        }
      ],
      "booksAccess": []
    },
    {
      "idBook": "7891",
      "created": "2018-08-13 01:59:50",
      "updated": "2018-10-01 14:13:19",
      "idBookType": "book",
      "idProductsVariations": "8610",
      "title": "\u0627\u0644\u0625\u0633\u0644\u0627\u0645 \u0648\u0627\u0644\u0642\u064a\u0645 \u0627\u0644\u062d\u0636\u0627\u0631\u064a\u0629 \u0627\u0644\u0645\u0639\u0627\u0635\u0631\u0629 \u0640 \u0627\u0644\u062f\u064a\u0645\u0642\u0631\u0627\u0637\u064a\u0629 \u0646\u0645\u0648\u0630\u062c\u0627",
      "titleEn": null,
      "idFileCover": "45408",
      "idFileContent": null,
      "annotation": "\u0643\u062a\u0627\u0628 \u064a\u062a\u062d\u062f\u062b \u0639\u0646 \u0627\u0644\u0642\u064a\u0645 \u0627\u0644\u062d\u0636\u0627\u0631\u064a\u0629 \u0627\u0644\u0625\u0633\u0644\u0627\u0645\u064a\u0629 ",
      "annotationEn": null,
      "idBookSeries": null,
      "seriesNumber": null,
      "ISBNEbook": null,
      "ISBNEbookLocked": "0",
      "ISBNPrinted": "",
      "ISBNMobi": null,
      "idPublisher": "1883",
      "uid": "902e2f77-9e9c-11e8-9223-901b0eed556c",
      "version": "14",
      "idLanguage": "ar",
      "canBeUsedInMinimart": "1",
      "autoCoverPage": null,
      "autoTitlePage": null,
      "autoCopyrightPage": null,
      "originalTitle": "",
      "publishingYear": "2016",
      "idFilePDFCover": null,
      "idPODOption": null,
      "printedIn": null,
      "designMode": "0",
      "ebookPublisher": null,
      "idUserExtSales": "11339",
      "sumItunes": null,
      "sumElib": null,
      "sumApp": null,
      "lastExtSalesMailDate": null,
      "idBookUploadAgent": null,
      "publishDate": "2018-10-01 14:13:19",
      "approveDate": "2018-08-22 18:02:40",
      "translitTitle": "",
      "translitAnnotation": "",
      "addUTMCodes": "0",
      "focusBookDate": null,
      "activityRating": "180",
      "deleted": "0",
      "referencePageCount": null,
      "referencePageCountIgnore": "0",
      "chapterCount": "12",
      "wordCount": "31884",
      "rtl": "1",
      "languageName": "Arabic",
      "idUser": "11339",
      "userLogin": "hamadasaad241@yahoo.com",
      "price": "1.00",
      "VAT": "0.0000",
      "currencyDesignation": "$",
      "priceConverted": "1.000000000",
      "VATConverted": "0.000000000",
      "currencyDesignationConverted": "$",
      "isBought": "0",
      "isFavorite": "0",
      "bwcCurrentPage": null,
      "bwcFontSize": null,
      "isMyBook": "0",
      "extSalesUpdated": "1",
      "adminTitle": "\u0627\u0644\u0625\u0633\u0644\u0627\u0645 \u0648\u0627\u0644\u0642\u064a\u0645 \u0627\u0644\u062d\u0636\u0627\u0631\u064a\u0629 \u0627\u0644\u0645\u0639\u0627\u0635\u0631\u0629 \u0640 \u0627\u0644\u062f\u064a\u0645\u0642\u0631\u0627\u0637\u064a\u0629 \u0646\u0645\u0648\u0630\u062c\u0627 [hamadasaad241@yahoo.com] {7891}",
      "KBHash": null,
      "mobi": "0",
      "epub": "0",
      "fb2": "0",
      "eNovella": "0",
      "PDF": "0",
      "POD": "0",
      "borrowedLibraryThisMonth": null,
      "borrowedUserThisMonth": null,
      "borrowCount": null,
      "haveLeaseInAnotherLibrary": null,
      "isLibraryUser": null,
      "budgetUsed": null,
      "coverFileData": "{\"idFile\":45408,\"ext\":\"png\",\"name\":\"\u0627\u0644\u0625\u0633\u0644\u0627\u0645 \u0648\u0627\u0644\u0642\u064a\u0645 \u0627\u0644\u062d\u0636\u0627\u0631\u064a\u0629 \u0627\u0644\u0645\u0639\u0627\u0635\u0631\u0629 \u0640 \u0627\u0644\u062f\u064a\u0645\u0642\u0631\u0627\u0637\u064a\u0629 \u0646\u0645\u0648\u0630\u062c\u0627\",\"width\":2464,\"height\":3048}",
      "bookAuthorsJSON": null,
      "bookGenresJSON": null,
      "booksAccessJSON": null,
      "images": [
        "45408"
      ],
      "bookAuthors": [
        {
          "caption": "\u0623\u062d\u0645\u062f \u0633\u0639\u062f \u0627\u0644\u0639\u0634",
          "email": "hamadasaad241@yahoo.com",
          "firstName": "\u0623\u062d\u0645\u062f",
          "homePage": null,
          "idAuthor": "6189",
          "lastName": "\u0627\u0644\u0639\u0634",
          "middleName": "\u0633\u0639\u062f",
          "nickname": "\u0627\u0644\u0639\u0634"
        }
      ],
      "bookGenres": [
        {
          "fb2Name": null,
          "idBook": "7891",
          "idBookGenre": "17597",
          "idGenre": "482",
          "name": "History and civilisations"
        }
      ],
      "booksAccess": []
    },
    {
      "idBook": "7920",
      "created": "2018-08-30 14:56:38",
      "updated": "2018-09-25 04:26:39",
      "idBookType": "book",
      "idProductsVariations": "8639",
      "title": "\u062f\u0644\u064a\u0644 \u0627\u0644\u062f\u0639\u0627\u0621",
      "titleEn": null,
      "idFileCover": "45514",
      "idFileContent": null,
      "annotation": "\u0643\u062a\u0627\u0628 \u0623\u062f\u0639\u064a\u0629",
      "annotationEn": null,
      "idBookSeries": null,
      "seriesNumber": null,
      "ISBNEbook": "978-603-02-3002-0",
      "ISBNEbookLocked": "0",
      "ISBNPrinted": "978-603-02-3002-0",
      "ISBNMobi": "978-603-02-3002-0",
      "idPublisher": "1912",
      "uid": "e5f227fc-ac64-11e8-9223-901b0eed556c",
      "version": "21",
      "idLanguage": "ar",
      "canBeUsedInMinimart": "1",
      "autoCoverPage": null,
      "autoTitlePage": null,
      "autoCopyrightPage": null,
      "originalTitle": null,
      "publishingYear": "2017",
      "idFilePDFCover": null,
      "idPODOption": null,
      "printedIn": null,
      "designMode": "0",
      "ebookPublisher": null,
      "idUserExtSales": "11475",
      "sumItunes": null,
      "sumElib": null,
      "sumApp": null,
      "lastExtSalesMailDate": null,
      "idBookUploadAgent": null,
      "publishDate": "2018-09-24 20:17:29",
      "approveDate": "2018-09-25 04:26:39",
      "translitTitle": null,
      "translitAnnotation": null,
      "addUTMCodes": "0",
      "focusBookDate": null,
      "activityRating": "141",
      "deleted": "0",
      "referencePageCount": null,
      "referencePageCountIgnore": "0",
      "chapterCount": "10",
      "wordCount": "14252",
      "rtl": "1",
      "languageName": "Arabic",
      "idUser": "11475",
      "userLogin": "mbahareth@gmail.com",
      "price": "1.00",
      "VAT": "0.0000",
      "currencyDesignation": "$",
      "priceConverted": "1.000000000",
      "VATConverted": "0.000000000",
      "currencyDesignationConverted": "$",
      "isBought": "0",
      "isFavorite": "0",
      "bwcCurrentPage": null,
      "bwcFontSize": null,
      "isMyBook": "0",
      "extSalesUpdated": "1",
      "adminTitle": "\u062f\u0644\u064a\u0644 \u0627\u0644\u062f\u0639\u0627\u0621 [mbahareth@gmail.com] {7920}",
      "KBHash": null,
      "mobi": "0",
      "epub": "0",
      "fb2": "0",
      "eNovella": "0",
      "PDF": "0",
      "POD": "0",
      "borrowedLibraryThisMonth": null,
      "borrowedUserThisMonth": null,
      "borrowCount": null,
      "haveLeaseInAnotherLibrary": null,
      "isLibraryUser": null,
      "budgetUsed": null,
      "coverFileData": "{\"idFile\":45514,\"ext\":\"png\",\"name\":\"\u062f\u0644\u064a\u0644 \u0627\u0644\u062f\u0639\u0627\u0621\",\"width\":328,\"height\":465}",
      "bookAuthorsJSON": null,
      "bookGenresJSON": null,
      "booksAccessJSON": null,
      "images": [
        "45514"
      ],
      "bookAuthors": [
        {
          "caption": "\u0645\u062d\u0645\u062f  \u0628\u0627\u062d\u0627\u0631\u062b",
          "email": "ask@mohammadbahareth.com",
          "firstName": "\u0645\u062d\u0645\u062f",
          "homePage": "mohammadbahareth.com",
          "idAuthor": "6264",
          "lastName": "\u0628\u0627\u062d\u0627\u0631\u062b",
          "middleName": null,
          "nickname": null
        }
      ],
      "bookGenres": [
        {
          "fb2Name": "religion_rel",
          "idBook": "7920",
          "idBookGenre": "17648",
          "idGenre": "132",
          "name": "Religion"
        },
        {
          "fb2Name": null,
          "idBook": "7920",
          "idBookGenre": "17647",
          "idGenre": "482",
          "name": "History and civilisations"
        }
      ],
      "booksAccess": []
    },
    {
      "idBook": "7791",
      "created": "2018-06-22 20:50:56",
      "updated": "2018-07-08 07:49:04",
      "idBookType": "book",
      "idProductsVariations": "8509",
      "title": "\u0635\u0641\u062d\u0627\u062a \u0645\u0634\u0631\u0642\u0629 \u0645\u0646 \u0627\u0644\u062a\u0627\u0631\u064a\u062e \u0627\u0644\u0625\u0633\u0644\u0627\u0645\u064a \u0627\u0644\u063a\u0627\u0626\u0628 \u0648\u0627\u0644\u0645\u0646\u0633\u064a \" \u0627\u0644\u0623\u0645\u0631\u064a\u0643\u062a\u0627\u0646 \u0642\u0628\u0644 \u0643\u0631\u064a\u0633\u062a\u0648\u0641\u0631 \u0643\u0648\u0644\u0648\u0645\u0628\u0648\u0633 \u0648\u0623\u0645\u0631\u064a\u0643\u0648 \u0641\u0633\u0628\u0648\u062a\u0634\u064a \"",
      "titleEn": null,
      "idFileCover": "45017",
      "idFileContent": null,
      "annotation": "\u064a\u062a\u062d\u062f\u062b \u0647\u0630\u0627 \u0627\u0644\u0643\u062a\u0627\u0628 \u0639\u0646 \u0625\u0643\u062a\u0634\u0627\u0641 \u0627\u0644\u0623\u0645\u0631\u064a\u0643\u062a\u064a\u0646 \u0642\u0628\u0644 \u0643\u0631\u064a\u0633\u062a\u0641\u0631 \u0643\u0648\u0644\u0648\u0645\u0628\u0648\u0633 \u060c \u0648\u064a\u062b\u0628\u062a \u0628\u0627\u0644\u0623\u062f\u0644\u0629 \u0643\u0630\u0628 \u0625\u0643\u062a\u0634\u0627\u0641 \u0627\u0644\u0623\u0645\u0631\u064a\u0643\u062a\u064a\u0646 \u0642\u0628\u0644 \u0643\u0648\u0644\u0648\u0645\u0628\u0648\u0633 \u060c \u0648\u064a\u0643\u0634\u0641 \u0627\u0644\u062d\u0642\u0627\u0626\u0642 \u0639\u0646 \u0627\u0644\u0647\u0646\u0648\u062f \u0627\u0644\u062d\u0645\u0631 \u0648 \u0627\u0644\u0645\u0630\u0627\u0628\u062d \u0627\u0644\u062a\u064a \u062a\u0639\u0631\u0636\u0648\u0627 \u0644\u0647\u0627 \u060c \u0628\u0627\u0644\u0625\u0636\u0627\u0641\u0629 \u0625\u0644\u0649 \u0627\u0644\u0625\u0628\u0627\u062f\u0629 \u0627\u0644\u062c\u0645\u0627\u0639\u064a\u0629 \u0648\u0627\u0644\u062a\u0637\u0647\u064a\u0631 \u0627\u0644\u0639\u0631\u0642\u064a.\n\u062e\u0631\u0627\u0626\u0637 \u0627\u0644\u0645\u0633\u0644\u0645\u064a\u0646 \u0645\u062b\u0644 \u062e\u0631\u064a\u0637\u0629 \u0627\u0644\u0625\u062f\u0631\u064a\u0633\u064a \u062a\u0643\u0634\u0641 \u062d\u0642\u064a\u0642\u0629 \u0623\u0646 \u0627\u0644\u0639\u0627\u0644\u0645 \u0643\u0627\u0646 \u0639\u0644\u0649 \u0639\u0644\u0645 \u062a\u0627\u0645 \u0628\u0648\u062c\u0648\u062f \u0627\u0644\u0623\u0645\u0631\u064a\u0643\u062a\u064a\u0646.\n\u0648\u064a\u062a\u0646\u0627\u0648\u0644 \u0627\u0644\u0643\u062a\u0627\u0628 \u0631\u062d\u0644\u0629 \u0627\u0644\u0633\u0644\u0637\u0627\u0646 \u0627\u0644\u0645\u0633\u0644\u0645 \u0623\u0628\u0648 \u0628\u0643\u0631 \u0627\u0644\u062b\u0627\u0646\u064a ( \u0633\u0644\u0637\u0627\u0646 \u0645\u0627\u0644\u064a \u0627\u0644\u0625\u0641\u0631\u064a\u0642\u064a\u0629 ) \u0627\u0644\u0645\u0644\u0642\u0628 \u0628\u0640 \u0645\u0644\u0643 \u0627\u0644\u0630\u0647\u0628 \u0625\u0644\u0649 \u0627\u0644\u0623\u0645\u0631\u064a\u0643\u062a\u064a\u0646 \u0644\u0625\u0643\u062a\u0634\u0627\u0641\u0647\u0627 \u0642\u0628\u0644 \u0643\u0631\u064a\u0633\u062a\u0641\u0631 \u0643\u0648\u0644\u0648\u0645\u0628\u0648\u0633 \u0628\u0639\u062f\u0629 \u0642\u0631\u0648\u0646.\n\n\u0648\u064a\u062c\u064a\u0628 \u0627\u0644\u0643\u062a\u0627\u0628 \u0639\u0644\u0649 \u0627\u0644\u0623\u0633\u0626\u0644\u0629 \u0627\u0644\u062a\u0627\u0644\u064a\u0629 :\n\u0623\u0648\u0644\u0627\u064b \u061b \u0647\u0644 \u0648\u0635\u0644 \u0627\u0644\u0645\u0633\u0644\u0645\u0648\u0646 \u0625\u0644\u0649 \u0627\u0644\u0623\u0645\u0631\u064a\u0643\u062a\u064a\u0646 \u0642\u0628\u0644 \u0643\u0631\u064a\u0633\u062a\u0641\u0631 \u0643\u0648\u0644\u0648\u0645\u0628\u0648\u0633 \u061f!\n\u062b\u0627\u0646\u064a\u0627\u064b \u061b \u0645\u0627 \u0647\u064a \u062d\u0642\u064a\u0642\u0629 \u0627\u0644\u0647\u0646\u0648\u062f \u0627\u0644\u062d\u0645\u0631 \u060c \u0633\u0643\u0627\u0646 \u0623\u0645\u0631\u064a\u0643\u0627 \u0627\u0644\u0623\u0635\u0644\u064a\u064a\u0646 \u061f! \u0648\u0645\u0627 \u0647\u0649 \u0623\u0639\u062f\u0627\u062f\u0647\u0645 \u061f! \u0648\u0647\u0644 \u062a\u0639\u0631\u0636\u0648\u0627 \u0644\u0644\u0645\u0630\u0627\u0628\u062d \u0627\u0644\u0639\u0631\u0642\u064a\u0629 \u0648\u0627\u0644\u0625\u0628\u0627\u062f\u0627\u062a \u0627\u0644\u062c\u0645\u0627\u0639\u064a\u0629 \u061f!\n\u062b\u0627\u0644\u062b\u0627\u064b \u061b \u0645\u0627\u0630\u0627 \u062a\u0642\u0648\u0644 \u062e\u0631\u0627\u0626\u0637 \u0627\u0644\u0645\u0633\u0644\u0645\u0648\u0646 \u0627\u0644\u0631\u062d\u0627\u0644\u0629 \u0645\u062b\u0644 \u0627\u0644\u0625\u062f\u0631\u064a\u0633\u064a \u0639\u0646 \u0627\u0644\u0623\u0645\u0631\u064a\u0643\u062a\u064a\u0646 \u061f!\n\u0631\u0627\u0628\u0639\u0627\u064b \u061b \u0645\u0627\u0630\u0627 \u062a\u0642\u0648\u0644 \u0627\u0644\u062f\u0648\u0642\u0629 \u0627\u0644\u0625\u0633\u0628\u0627\u0646\u064a\u0629 \u0644\u0648\u064a\u0632\u0627 \u0625\u064a\u0632\u0627\u0628\u064a\u0644  \u061f! \u0648\u0645\u0627\u0630\u0627 \u064a\u0642\u0648\u0644 \u0627\u0644\u0645\u0624\u0631\u062e \u0627\u0644\u0625\u0646\u062c\u0644\u064a\u0632\u064a \u0634\u0644\u064a\u062f\u0631\u064a\u0643  \u061f!\n\u062e\u0627\u0645\u0633\u0627\u064b \u061b \u0623\u0637\u0644\u0633 \u062a\u0627\u0631\u064a\u062e \u0627\u0644\u0625\u0633\u0644\u0627\u0645.\n\u0633\u0627\u062f\u0633\u0627\u064b \u061b \u062d\u0642\u0627\u0626\u0642 \u0644\u0627 \u062a\u0642\u0628\u0644 \u0627\u0644\u062c\u062f\u0627\u0644.\n",
      "annotationEn": null,
      "idBookSeries": null,
      "seriesNumber": null,
      "ISBNEbook": null,
      "ISBNEbookLocked": "0",
      "ISBNPrinted": null,
      "ISBNMobi": "9780463952719",
      "idPublisher": "1812",
      "uid": "f5f8a14f-765d-11e8-9223-901b0eed556c",
      "version": "82",
      "idLanguage": "ar",
      "canBeUsedInMinimart": "1",
      "autoCoverPage": null,
      "autoTitlePage": null,
      "autoCopyrightPage": null,
      "originalTitle": null,
      "publishingYear": "2018",
      "idFilePDFCover": null,
      "idPODOption": "9633",
      "printedIn": null,
      "designMode": "0",
      "ebookPublisher": null,
      "idUserExtSales": "11246",
      "sumItunes": null,
      "sumElib": null,
      "sumApp": null,
      "lastExtSalesMailDate": null,
      "idBookUploadAgent": null,
      "publishDate": "2018-07-08 07:22:54",
      "approveDate": "2018-07-08 07:49:04",
      "translitTitle": null,
      "translitAnnotation": null,
      "addUTMCodes": "1",
      "focusBookDate": null,
      "activityRating": "168",
      "deleted": "0",
      "referencePageCount": null,
      "referencePageCountIgnore": "0",
      "chapterCount": "14",
      "wordCount": "3995",
      "rtl": "1",
      "languageName": "Arabic",
      "idUser": "11246",
      "userLogin": "ahmedmohamed_s711@yahoo.com",
      "price": "3.99",
      "VAT": "0.0000",
      "currencyDesignation": "$",
      "priceConverted": "3.990000000",
      "VATConverted": "0.000000000",
      "currencyDesignationConverted": "$",
      "isBought": "0",
      "isFavorite": "0",
      "bwcCurrentPage": null,
      "bwcFontSize": null,
      "isMyBook": "0",
      "extSalesUpdated": "1",
      "adminTitle": "\u0635\u0641\u062d\u0627\u062a \u0645\u0634\u0631\u0642\u0629 \u0645\u0646 \u0627\u0644\u062a\u0627\u0631\u064a\u062e \u0627\u0644\u0625\u0633\u0644\u0627\u0645\u064a \u0627\u0644\u063a\u0627\u0626\u0628 \u0648\u0627\u0644\u0645\u0646\u0633\u064a \" \u0627\u0644\u0623\u0645\u0631\u064a\u0643\u062a\u0627\u0646 \u0642\u0628\u0644 \u0643\u0631\u064a\u0633\u062a\u0648\u0641\u0631 \u0643\u0648\u0644\u0648\u0645\u0628\u0648\u0633 \u0648\u0623\u0645\u0631\u064a\u0643\u0648 \u0641\u0633\u0628\u0648\u062a\u0634\u064a \" [ahmedmohamed_s711@yahoo.com] {7791}",
      "KBHash": null,
      "mobi": "0",
      "epub": "0",
      "fb2": "0",
      "eNovella": "0",
      "PDF": "0",
      "POD": "0",
      "borrowedLibraryThisMonth": null,
      "borrowedUserThisMonth": null,
      "borrowCount": null,
      "haveLeaseInAnotherLibrary": null,
      "isLibraryUser": null,
      "budgetUsed": null,
      "coverFileData": "{\"idFile\":45017,\"ext\":\"jpg\",\"name\":\"\u0635\u0641\u062d\u0627\u062a \u0645\u0634\u0631\u0642\u0629 \u0645\u0646 \u0627\u0644\u062a\u0627\u0631\u064a\u062e \u0627\u0644\u0625\u0633\u0644\u0627\u0645\u064a \u0627\u0644\u063a\u0627\u0626\u0628 \u0648\u0627\u0644\u0645\u0646\u0633\u064a \\\" \u0627\u0644\u0623\u0645\u0631\u064a\u0643\u062a\u0627\u0646 \u0642\u0628\u0644 \u0643\u0631\u064a\u0633\u062a\u0648\u0641\u0631 \u0643\u0648\u0644\u0648\u0645\u0628\u0648\u0633 \u0648\u0623\u0645\u0631\u064a\u0643\u0648 \u0641\u0633\u0628\u0648\u062a\u0634\u064a \\\"\",\"width\":4500,\"height\":6649}",
      "bookAuthorsJSON": null,
      "bookGenresJSON": null,
      "booksAccessJSON": null,
      "images": [
        "45017"
      ],
      "bookAuthors": [
        {
          "caption": "\u0623\u062d\u0645\u062f  \u0645\u062d\u0645\u062f \u0635\u0641\u0648\u062a",
          "email": "ahmedmohamed_s711@yahoo.com",
          "firstName": "\u0623\u062d\u0645\u062f",
          "homePage": "https:\/\/theshipofnoah.blogspot.com\/",
          "idAuthor": "6108",
          "lastName": "\u0645\u062d\u0645\u062f \u0635\u0641\u0648\u062a",
          "middleName": null,
          "nickname": null
        }
      ],
      "bookGenres": [
        {
          "fb2Name": null,
          "idBook": "7791",
          "idBookGenre": "17429",
          "idGenre": "482",
          "name": "History and civilisations"
        }
      ],
      "booksAccess": []
    },
    {
      "idBook": "7788",
      "created": "2018-06-22 14:05:38",
      "updated": "2018-07-08 07:49:03",
      "idBookType": "book",
      "idProductsVariations": "8506",
      "title": "\u062f\u0631\u0648\u0633 \u0648\u0639\u0628\u0631 \u0645\u0646 \u0642\u0635\u0629 \u0627\u0644\u0640 47 \u0631\u0648\u0646\u064a\u0646 \" \u0627\u0644\u0623\u0633\u0637\u0648\u0631\u0629 \u0627\u0644\u064a\u0627\u0628\u0627\u0646\u064a\u0629 \u0627\u0644\u062e\u0627\u0644\u062f\u0629 \"",
      "titleEn": null,
      "idFileCover": "45002",
      "idFileContent": null,
      "annotation": "\u064a\u064f\u062d\u0643\u0649 \u0623\u0646 \u0642\u0627\u0626\u062f \u0643\u0628\u064a\u0631 \" \u0627\u0644\u0644\u0648\u0631\u062f \" \u0645\u0646 \u0642\u0627\u062f\u0629 \u0627\u0644\u064a\u0627\u0628\u0627\u0646 \u0627\u0644\u0639\u0638\u0627\u0645 \u0641\u064a \u0628\u062f\u0627\u064a\u0629 \u0627\u0644\u0642\u0631\u0646 \u0627\u0644\u062b\u0627\u0645\u0646 \u0639\u0634\u0631 \u064a\u064f\u062f\u0639\u0649 \" \u062f\u0627\u0645\u064a\u0648 \" \u0643\u0627\u0646 \u0644\u062f\u064a\u0647 \u0645\u0646 \u0627\u0644\u0623\u062a\u0628\u0627\u0639 \u061b 47 \u0633\u0627\u0645\u0648\u0631\u0627\u064a ( \u0627\u0644\u0633\u0627\u0645\u0648\u0631\u0627\u064a \u0647\u0648 \u0645\u0635\u0637\u0644\u062d \u0641\u064a \u0627\u0644\u064a\u0627\u0628\u0627\u0646 \u064a\u064f\u0637\u0644\u0642 \u0639\u0644\u0649 \u0627\u0644\u0641\u0627\u0631\u0633 \u0627\u0644\u0634\u062c\u0627\u0639 \u0623\u0648 \u0631\u062a\u0628\u0629 \u0639\u0633\u0643\u0631\u064a\u0629 \u0631\u0641\u064a\u0639\u0629 \u0627\u0644\u0645\u0633\u062a\u0648\u0649 \u0623\u0648 \u0627\u0644\u0642\u0627\u0626\u062f \u0627\u0644\u0645\u062d\u062a\u0631\u0645 \u0628\u064a\u0646 \u0642\u0648\u0645\u0647 ) .. \u0644\u0643\u0646 \u0647\u0630\u0627 \u0627\u0644\u0633\u064a\u062f \u0642\u062f \u062a\u0645 \u062e\u062f\u0627\u0639\u0647 \u0639\u0646 \u0637\u0631\u064a\u0642 \u0627\u0644\u0633\u062d\u0631 \u0644\u064a\u0642\u062a\u0644 \u0645\u0633\u0626\u0648\u0644\u0627\u064b \u0641\u064a \u0627\u0644\u062d\u0643\u0648\u0645\u0629 \u0623\u0639\u0632\u0644 \u0645\u0646 \u0627\u0644\u0633\u0644\u0627\u062d \u064a\u064f\u062f\u0639\u0649 \" \u0643\u064a\u0631\u0627 \" \u060c \u0648\u0647\u0648 \u0645\u0627 \u064a\u064f\u0639\u062a\u0628\u0631 \u0623\u0645\u0631\u0627\u064b \u0645\u064f\u062e\u0627\u0644\u0641\u0627\u064b \u0644\u0642\u0627\u0646\u0648\u0646 \u0627\u0644\u062f\u0648\u0644\u0629 \u0648\u0643\u0630\u0644\u0643 \u0645\u062e\u0627\u0644\u0641\u0627\u064b \u0644\u062a\u0642\u0627\u0644\u064a\u062f \u0648\u0623\u062e\u0644\u0627\u0642 \u0627\u0644\u0633\u0627\u0645\u0648\u0631\u0627\u064a \u061b \u062d\u064a\u062b \u0644\u0627 \u064a\u0635\u062d \u0623\u0628\u062f\u0627\u064b \u0627\u0644\u062a\u0639\u062f\u064a \u0628\u0627\u0644\u0633\u0644\u0627\u062d \u0639\u0644\u0649 \u0631\u062c\u0644 \u0623\u0639\u0632\u0644 .. \u0641\u062d\u064f\u0643\u0645 \u0639\u0644\u064a\u0647 \u0628\u0627\u0644\u0645\u0648\u062a ( \u0627\u0644\u0625\u0639\u062f\u0627\u0645 ) .. \u0648\u0644\u0623\u0646 \" \u062f\u0627\u0645\u064a\u0648 \" \u0643\u0627\u0646 \u0642\u0627\u0626\u062f\u0627\u064b \u0645\u0647\u0645\u0627\u064b \u0645\u0646 \u0642\u0627\u062f\u0627\u062a \u0627\u0644\u0645\u062c\u062a\u0645\u0639 \u0627\u0644\u064a\u0627\u0628\u0627\u0646\u064a \u0641\u0644\u0627 \u064a\u0645\u0643\u0646 \u0642\u062a\u0644\u0647 \u0623\u0648 \u0625\u0639\u062f\u0627\u0645\u0647 \u0643\u0628\u0627\u0642\u064a \u0627\u0644\u0646\u0627\u0633 .. \u0641\u0625\u062e\u062a\u0627\u0631 \u0647\u0630\u0627 \u0627\u0644\u0642\u0627\u0626\u062f \" \u062f\u0627\u0645\u064a\u0648 \" \u0623\u0646 \u064a\u0645\u0648\u062a \u0645\u064f\u0646\u062a\u062d\u0631\u0627\u064b \u0628\u064a\u062f\u0647 \u0648\u0628\u0633\u064a\u0641\u0647 \" \u0625\u0646\u062a\u062d\u0627\u0631 \u0637\u0642\u0648\u0633\u064a \" \u062d\u062a\u0649 \u064a\u0645\u0648\u062a \u0628\u0634\u0631\u0641 \u2013 \u0643\u0645\u0627 \u064a\u0639\u062a\u0642\u062f - \u060c \u0648\u062d\u062a\u0649 \u0644\u0627 \u064a\u064f\u0637\u0627\u0644\u0628 \u0623\u062a\u0628\u0627\u0639\u0647 \u0628\u062f\u0645\u0647 \u0643\u0639\u0627\u062f\u0629 \u0627\u0644\u0633\u0627\u0645\u0648\u0631\u064a \u0639\u0646\u062f\u0647\u0645 \u0641\u064a \u0627\u0644\u064a\u0627\u0628\u0627\u0646 ... !!\n\n\u0641\u0625\u062c\u062a\u0645\u0639 \u0627\u0644\u0644\u0648\u0631\u062f \" \u062f\u0627\u0645\u064a\u0648 \" \u0628\u0623\u062a\u0628\u0627\u0639\u0647 \u0627\u0644\u0640 47 \u0633\u0627\u0645\u0648\u0631\u064a \u0641\u064a \u0633\u0627\u062d\u0629 \u0643\u0628\u064a\u0631\u0629 \u0645\u0646 \u0645\u0642\u0627\u0637\u0639\u062a\u0647 \u0627\u0644\u064a\u0627\u0628\u0627\u0646\u064a\u0629 \u0644\u062a\u0646\u0641\u064a\u0630 \u062d\u0643\u0645 \u0627\u0644\u0625\u0639\u062f\u0627\u0645 \u0639\u0644\u0649 \u0646\u0641\u0633\u0647 \u0623\u0645\u0627\u0645 \u062d\u0634\u062f \u0643\u0628\u064a\u0631 \u0645\u0646 \u0634\u0639\u0628\u0647 .. \u0648\u0639\u0646\u062f\u0645\u0627 \u0645\u0627\u062a \u2013 \u0642\u062a\u0644 \u0646\u0641\u0633\u0647 - \u0647\u0630\u0627 \u0627\u0644\u0642\u0627\u0626\u062f \u0627\u0644\u0643\u0628\u064a\u0631 \u0628\u064a\u062f\u0647 \u0623\u0645\u0627\u0645 \u0639\u0634\u064a\u0631\u062a\u0647 \u0648\u0628\u064a\u0646 \u062c\u0646\u0648\u062f\u0647 \u0648\u0623\u062a\u0628\u0627\u0639\u0647 \u061b \u0623\u0635\u0628\u062d \u0627\u0644\u0633\u0627\u0645\u0648\u0631\u064a \u0627\u0644\u0630\u064a\u0646 \u0639\u062f\u062f\u0647\u0645 47 \u0628\u062f\u0648\u0646 \u0633\u064a\u062f \u061b \u0647\u0646\u0627 \u0641\u0642\u0637 \u064a\u064f\u0635\u0628\u062d \u0627\u0644\u0633\u0627\u0645\u0648\u0631\u0627\u064a \u0628\u0644\u0627 \u0642\u064a\u0645\u0629 \u0648\u0628\u0644\u0627 \u0645\u0646\u0632\u0644\u0629 \u0641\u064a \u0627\u0644\u0645\u062c\u062a\u0645\u0639 \u0627\u0644\u064a\u0627\u0628\u0627\u0646\u064a \u0643\u0645\u0627 \u062c\u0631\u062a \u0627\u0644\u0639\u0627\u062f\u0629 \u0648\u0643\u0645\u0627 \u0647\u0649 \u0627\u0644\u062a\u0642\u0627\u0644\u064a\u062f \u0639\u0646\u062f\u0647\u0645 \u061b \u062d\u064a\u062b \u064a\u064f\u062c\u0631\u062f\u0648\u0646 \u0645\u0646 \u0623\u0633\u0644\u062d\u062a\u0647\u0645 \u0648\u0645\u0646\u0627\u0635\u0628\u0647\u0645 \u0648\u0623\u0648\u0633\u0645\u062a\u0647\u0645 \u0648\u0623\u0645\u0644\u0627\u0643\u0647\u0645 \u060c \u0648\u064a\u064f\u0637\u0631\u062f\u0648\u0646 \u062e\u0627\u0631\u062c \u0628\u0644\u0627\u062f\u0647\u0645 \u060c \u0648\u064a\u064f\u0637\u0644\u0642 \u0639\u0644\u064a\u0647\u0645 \" \u0627\u0644\u0631\u0648\u0646\u064a\u0646 \" \u060c \u0648\u0647\u0646\u0627 \u0641\u0642\u0637 \u062a\u062d\u0648\u0644 47 \u0633\u0627\u0645\u0648\u0631\u0627\u064a \u0625\u0644\u0649 \" 47 \u0631\u0648\u0646\u064a\u0646 \".\n\u0644\u0643\u0646 \u0645\u0627 \u062d\u062f\u062b ..... \n\n\u0647\u064a\u0627 \u0628\u0646\u0627 \u0646\u062a\u0639\u0631\u0641 \u0639\u0644\u0649 \u0628\u0627\u0642\u064a \u0627\u0644\u0642\u0635\u0629 \u060c \u0648\u0646\u0633\u062a\u0644\u0647\u0645 \u0645\u0646\u0647\u0627 \u0627\u0644\u062f\u0631\u0648\u0633 \u0648\u0627\u0644\u0639\u0628\u0631.",
      "annotationEn": null,
      "idBookSeries": null,
      "seriesNumber": null,
      "ISBNEbook": null,
      "ISBNEbookLocked": "0",
      "ISBNPrinted": null,
      "ISBNMobi": "9780463783870",
      "idPublisher": "1812",
      "uid": "571788ff-7625-11e8-9223-901b0eed556c",
      "version": "78",
      "idLanguage": "ar",
      "canBeUsedInMinimart": "1",
      "autoCoverPage": null,
      "autoTitlePage": null,
      "autoCopyrightPage": null,
      "originalTitle": null,
      "publishingYear": "2018",
      "idFilePDFCover": null,
      "idPODOption": "9633",
      "printedIn": null,
      "designMode": "0",
      "ebookPublisher": null,
      "idUserExtSales": "11246",
      "sumItunes": null,
      "sumElib": null,
      "sumApp": null,
      "lastExtSalesMailDate": null,
      "idBookUploadAgent": null,
      "publishDate": "2018-07-08 07:24:16",
      "approveDate": "2018-07-08 07:49:03",
      "translitTitle": null,
      "translitAnnotation": null,
      "addUTMCodes": "1",
      "focusBookDate": null,
      "activityRating": "211",
      "deleted": "0",
      "referencePageCount": null,
      "referencePageCountIgnore": "0",
      "chapterCount": "13",
      "wordCount": "2321",
      "rtl": "1",
      "languageName": "Arabic",
      "idUser": "11246",
      "userLogin": "ahmedmohamed_s711@yahoo.com",
      "price": "2.99",
      "VAT": "0.0000",
      "currencyDesignation": "$",
      "priceConverted": "2.990000000",
      "VATConverted": "0.000000000",
      "currencyDesignationConverted": "$",
      "isBought": "0",
      "isFavorite": "0",
      "bwcCurrentPage": null,
      "bwcFontSize": null,
      "isMyBook": "0",
      "extSalesUpdated": "1",
      "adminTitle": "\u062f\u0631\u0648\u0633 \u0648\u0639\u0628\u0631 \u0645\u0646 \u0642\u0635\u0629 \u0627\u0644\u0640 47 \u0631\u0648\u0646\u064a\u0646 \" \u0627\u0644\u0623\u0633\u0637\u0648\u0631\u0629 \u0627\u0644\u064a\u0627\u0628\u0627\u0646\u064a\u0629 \u0627\u0644\u062e\u0627\u0644\u062f\u0629 \" [ahmedmohamed_s711@yahoo.com] {7788}",
      "KBHash": null,
      "mobi": "0",
      "epub": "0",
      "fb2": "0",
      "eNovella": "0",
      "PDF": "0",
      "POD": "0",
      "borrowedLibraryThisMonth": null,
      "borrowedUserThisMonth": null,
      "borrowCount": null,
      "haveLeaseInAnotherLibrary": null,
      "isLibraryUser": null,
      "budgetUsed": null,
      "coverFileData": "{\"idFile\":45002,\"ext\":\"jpg\",\"name\":\"\u062f\u0631\u0648\u0633 \u0648\u0639\u0628\u0631 \u0645\u0646 \u0642\u0635\u0629 \u0627\u0644\u0640 47 \u0631\u0648\u0646\u064a\u0646 \\\" \u0627\u0644\u0623\u0633\u0637\u0648\u0631\u0629 \u0627\u0644\u064a\u0627\u0628\u0627\u0646\u064a\u0629 \u0627\u0644\u062e\u0627\u0644\u062f\u0629 \\\"\",\"width\":3500,\"height\":4375}",
      "bookAuthorsJSON": null,
      "bookGenresJSON": null,
      "booksAccessJSON": null,
      "images": [
        "45002"
      ],
      "bookAuthors": [
        {
          "caption": "\u0623\u062d\u0645\u062f  \u0645\u062d\u0645\u062f \u0635\u0641\u0648\u062a",
          "email": "ahmedmohamed_s711@yahoo.com",
          "firstName": "\u0623\u062d\u0645\u062f",
          "homePage": "https:\/\/theshipofnoah.blogspot.com\/",
          "idAuthor": "6108",
          "lastName": "\u0645\u062d\u0645\u062f \u0635\u0641\u0648\u062a",
          "middleName": null,
          "nickname": null
        }
      ],
      "bookGenres": [
        {
          "fb2Name": null,
          "idBook": "7788",
          "idBookGenre": "17430",
          "idGenre": "482",
          "name": "History and civilisations"
        }
      ],
      "booksAccess": []
    },
    {
      "idBook": "6692",
      "created": "2018-02-02 19:36:43",
      "updated": "2018-06-17 14:23:50",
      "idBookType": "book",
      "idProductsVariations": "7406",
      "title": "\u0645\u0646\u0637\u0642\u0629 \u0623\u064e\u0632\u064e\u0648\u064e\u0627\u063a\u0652 \u0628\u0627\u0644\u0646\u064a\u062c\u0631- 1898- 1960\u0645: \u062f\u0631\u0627\u0633\u0629 \u062a\u0627\u0631\u064a\u062e\u064a\u0629 \u062d\u0636\u0627\u0631\u064a\u0629",
      "titleEn": null,
      "idFileCover": "43502",
      "idFileContent": null,
      "annotation": "\u0627\u0644\u062a\u0627\u0631\u064a\u062e \u0648\u0627\u0644\u062d\u0636\u0627\u0631\u0629- \u0645\u0642\u0627\u0648\u0645\u0629 \u0627\u0644\u0627\u0633\u062a\u0639\u0645\u0627\u0631 \u0641\u064a \u0625\u0641\u0631\u064a\u0642\u064a\u0627",
      "annotationEn": null,
      "idBookSeries": null,
      "seriesNumber": null,
      "ISBNEbook": "",
      "ISBNEbookLocked": "0",
      "ISBNPrinted": "",
      "ISBNMobi": "ISBN \u0645\u0646 \u0623\u062c\u0644 MOBI",
      "idPublisher": "1515",
      "uid": "65a97214-0850-11e8-805c-901b0eed556c",
      "version": "315",
      "idLanguage": "ar",
      "canBeUsedInMinimart": "1",
      "autoCoverPage": null,
      "autoTitlePage": null,
      "autoCopyrightPage": null,
      "originalTitle": "L\u2019Azawagh Nig\u00e9rien 1898-1960 ",
      "publishingYear": "2018",
      "idFilePDFCover": null,
      "idPODOption": "7843",
      "printedIn": "",
      "designMode": "0",
      "ebookPublisher": null,
      "idUserExtSales": "10390",
      "sumItunes": null,
      "sumElib": null,
      "sumApp": null,
      "lastExtSalesMailDate": null,
      "idBookUploadAgent": null,
      "publishDate": "2018-06-17 14:23:50",
      "approveDate": "2018-02-05 16:06:03",
      "translitTitle": "Mantiqatu Azawagh bin Niger 1898-1960",
      "translitAnnotation": "Salao Alassane",
      "addUTMCodes": "0",
      "focusBookDate": null,
      "activityRating": "708",
      "deleted": "0",
      "referencePageCount": null,
      "referencePageCountIgnore": "0",
      "chapterCount": "23",
      "wordCount": "41867",
      "rtl": "1",
      "languageName": "Arabic",
      "idUser": "10390",
      "userLogin": "salaoalassan@gmail.com",
      "price": "10.00",
      "VAT": "0.0000",
      "currencyDesignation": "$",
      "priceConverted": "10.000000000",
      "VATConverted": "0.000000000",
      "currencyDesignationConverted": "$",
      "isBought": "0",
      "isFavorite": "0",
      "bwcCurrentPage": null,
      "bwcFontSize": null,
      "isMyBook": "0",
      "extSalesUpdated": "1",
      "adminTitle": "\u0645\u0646\u0637\u0642\u0629 \u0623\u064e\u0632\u064e\u0648\u064e\u0627\u063a\u0652 \u0628\u0627\u0644\u0646\u064a\u062c\u0631- 1898- 1960\u0645: \u062f\u0631\u0627\u0633\u0629 \u062a\u0627\u0631\u064a\u062e\u064a\u0629 \u062d\u0636\u0627\u0631\u064a\u0629 [salaoalassan@gmail.com] {6692}",
      "KBHash": null,
      "mobi": "0",
      "epub": "0",
      "fb2": "0",
      "eNovella": "0",
      "PDF": "0",
      "POD": "0",
      "borrowedLibraryThisMonth": null,
      "borrowedUserThisMonth": null,
      "borrowCount": null,
      "haveLeaseInAnotherLibrary": null,
      "isLibraryUser": null,
      "budgetUsed": null,
      "coverFileData": "{\"idFile\":43502,\"ext\":\"jpg\",\"name\":\"\u0645\u0646\u0637\u0642\u0629 \u0623\u064e\u0632\u064e\u0648\u064e\u0627\u063a\u0652 \u0628\u0627\u0644\u0646\u064a\u062c\u0631- 1898- 1960\u0645: \u062f\u0631\u0627\u0633\u0629 \u062a\u0627\u0631\u064a\u062e\u064a\u0629 \u062d\u0636\u0627\u0631\u064a\u0629\",\"width\":2480,\"height\":3508}",
      "bookAuthorsJSON": null,
      "bookGenresJSON": null,
      "booksAccessJSON": null,
      "images": [
        "43502"
      ],
      "bookAuthors": [
        {
          "caption": "\u0633\u0627\u0644\u0648 \u0627\u0644\u062d\u0633\u0646 -",
          "email": "salaoalassan@gmail.com",
          "firstName": "\u0633\u0627\u0644\u0648",
          "homePage": null,
          "idAuthor": "5132",
          "lastName": "-",
          "middleName": "\u0627\u0644\u062d\u0633\u0646",
          "nickname": "-"
        }
      ],
      "bookGenres": [
        {
          "fb2Name": null,
          "idBook": "6692",
          "idBookGenre": "16906",
          "idGenre": "482",
          "name": "History and civilisations"
        }
      ],
      "booksAccess": []
    },
    {
      "idBook": "5938",
      "created": "2017-12-04 10:06:40",
      "updated": "2018-03-25 10:53:06",
      "idBookType": "book",
      "idProductsVariations": "6650",
      "title": "\u062a\u064a\u063a\u0627\u0644\u064a\u0646 - \u062d\u0644\u0645 \u0627\u0644\u0639\u0648\u062f\u0629",
      "titleEn": null,
      "idFileCover": "36565",
      "idFileContent": null,
      "annotation": "\u0633\u064a\u0633\u0648\u062f\u0643\u0645 \u0627\u0644\u0639\u0627\u0644\u0645\u060c \u0648\u064a\u062d\u0643\u0645\u0643\u0645 \u0627\u0644\u0623\u063a\u064a\u0627\u0631\u060c \u0648\u062a\u0645\u062c\u062f\u0648\u0646 \u0644\u0627\u0634\u064a\u0626\u064a\u0627\u062a \u0645\u0646 \u0634\u062a\u0649 \u0627\u0644\u0645\u0644\u0644 \u0648\u0627\u0644\u0639\u0642\u0627\u0626\u062f \u0648\u0627\u0644\u0646\u062d\u0644\u060c \u062e\u0637\u0631 \u0639\u0644\u064a\u0643\u0645 \u0644\u0627 \u062a\u062d\u0630\u0631\u0648\u0647\u0645 \u0648\u0644\u0627 \u062a\u0628\u062a\u0639\u062f\u0648\u0646 \u0639\u0646\u0647\u0645\u060c \u0641\u0625\u0646 \u0623\u064f\u062d\u064a\u0637\u064e \u0628\u0643\u0645 \u0641\u0623\u064a\u0642\u0646\u0648\u0627 \u0623\u0646\u0647 \u0645\u0645\u0627 \u0643\u0633\u0628\u062a\u0647 \u0623\u064a\u062f\u064a\u0643\u0645\u060c  \u0641\u0644\u0627 \u062a\u0644\u0648\u0645\u0648\u0627 \u0623\u062d\u062f\u0627 \u0648\u0644\u0648\u0645\u0648\u0627 \u0623\u0646\u0641\u0633\u0643\u0645.",
      "annotationEn": null,
      "idBookSeries": null,
      "seriesNumber": null,
      "ISBNEbook": null,
      "ISBNEbookLocked": "0",
      "ISBNPrinted": null,
      "ISBNMobi": null,
      "idPublisher": "1288",
      "uid": "d27bdc82-d8da-11e7-aa7d-001d92661257",
      "version": "165",
      "idLanguage": "ar",
      "canBeUsedInMinimart": "1",
      "autoCoverPage": null,
      "autoTitlePage": null,
      "autoCopyrightPage": null,
      "originalTitle": null,
      "publishingYear": "2017",
      "idFilePDFCover": null,
      "idPODOption": null,
      "printedIn": null,
      "designMode": "0",
      "ebookPublisher": null,
      "idUserExtSales": "6550",
      "sumItunes": null,
      "sumElib": null,
      "sumApp": null,
      "lastExtSalesMailDate": null,
      "idBookUploadAgent": null,
      "publishDate": "2018-01-16 21:28:20",
      "approveDate": "2017-12-06 06:00:22",
      "translitTitle": null,
      "translitAnnotation": null,
      "addUTMCodes": "0",
      "focusBookDate": null,
      "activityRating": "438",
      "deleted": "0",
      "referencePageCount": "308",
      "referencePageCountIgnore": "0",
      "chapterCount": "36",
      "wordCount": "48715",
      "rtl": "1",
      "languageName": "Arabic",
      "idUser": "6550",
      "userLogin": "arabiclibrary2017@gmail.com",
      "price": "2.00",
      "VAT": "0.0000",
      "currencyDesignation": "$",
      "priceConverted": "2.000000000",
      "VATConverted": "0.000000000",
      "currencyDesignationConverted": "$",
      "isBought": "0",
      "isFavorite": "0",
      "bwcCurrentPage": null,
      "bwcFontSize": null,
      "isMyBook": "0",
      "extSalesUpdated": "1",
      "adminTitle": "\u062a\u064a\u063a\u0627\u0644\u064a\u0646 - \u062d\u0644\u0645 \u0627\u0644\u0639\u0648\u062f\u0629 [arabiclibrary2017@gmail.com] {5938}",
      "KBHash": null,
      "mobi": "0",
      "epub": "0",
      "fb2": "0",
      "eNovella": "0",
      "PDF": "0",
      "POD": "0",
      "borrowedLibraryThisMonth": null,
      "borrowedUserThisMonth": null,
      "borrowCount": null,
      "haveLeaseInAnotherLibrary": null,
      "isLibraryUser": null,
      "budgetUsed": null,
      "coverFileData": "{\"idFile\":36565,\"ext\":\"jpg\",\"name\":\"\u062a\u064a\u063a\u0627\u0644\u064a\u0646 - \u062d\u0644\u0645 \u0627\u0644\u0639\u0648\u062f\u0629\",\"width\":1654,\"height\":2362}",
      "bookAuthorsJSON": null,
      "bookGenresJSON": null,
      "booksAccessJSON": null,
      "images": [
        "36565"
      ],
      "bookAuthors": [
        {
          "caption": "\u064a\u0627\u0633\u064a\u0646  \u0643\u0646\u064a",
          "email": null,
          "firstName": "\u064a\u0627\u0633\u064a\u0646",
          "homePage": null,
          "idAuthor": "4407",
          "lastName": "\u0643\u0646\u064a",
          "middleName": null,
          "nickname": null
        }
      ],
      "bookGenres": [
        {
          "fb2Name": "sci_history",
          "idBook": "5938",
          "idBookGenre": "16846",
          "idGenre": "390",
          "name": "History"
        },
        {
          "fb2Name": null,
          "idBook": "5938",
          "idBookGenre": "16847",
          "idGenre": "482",
          "name": "History and civilisations"
        },
        {
          "fb2Name": null,
          "idBook": "5938",
          "idBookGenre": "16849",
          "idGenre": "483",
          "name": "Novels and stories"
        },
        {
          "fb2Name": null,
          "idBook": "5938",
          "idBookGenre": "16848",
          "idGenre": "487",
          "name": "Biographies and diaries"
        }
      ],
      "booksAccess": []
    },
    {
      "idBook": "5256",
      "created": "2017-08-27 15:19:32",
      "updated": "2018-02-27 12:42:47",
      "idBookType": "book",
      "idProductsVariations": "5968",
      "title": "\u0627\u0644\u0639\u0631\u0627\u0642 \u0648\u0627\u0644\u0625\u0635\u0644\u0627\u062d",
      "titleEn": null,
      "idFileCover": "32958",
      "idFileContent": null,
      "annotation": "\u0627\u0648\u062c\u0627\u0639 \u0627\u0644\u0639\u0631\u0627\u0642 \u0648\u0643\u0627\u0631\u062b\u0629 \u0627\u0644\u0641\u0633\u0627\u062f. \u062d\u0643\u0627\u064a\u0629 \u0627\u0635\u0648\u0627\u062a \u062a\u0646\u0627\u062f\u064a \u0628\u0627\u0644\u0627\u0635\u0644\u0627\u062d \u0648\u0627\u062e\u0631\u0649 \u062a\u0633\u0628\u062d \u0644\u0644\u0641\u0633\u0627\u062f. \u0644\u0645\u0627\u0630\u0627 \u0627\u0644\u062a\u0638\u0627\u0647\u0631\u0627\u062a\u061f \u0648\u0645\u0627\u0630\u0627 \u064a\u0631\u064a\u062f \u0627\u0644\u0645\u062a\u0638\u0627\u0647\u0631\u0648\u0646\u061f \u0647\u0644 \u062d\u0642\u0642\u062a \u0627\u0644\u062a\u0638\u0627\u0647\u0631\u0627\u062a \u0633\u064a\u0627\u062f\u0629 \u0627\u0644\u0634\u0639\u0628\u061f \u0647\u0644 \u0646\u062c\u062d \u0627\u0644\u0645\u062a\u0638\u0627\u0647\u0631\u0648\u0646 \u0641\u064a \u062a\u062d\u062c\u064a\u0645 \u0627\u0644\u0639\u0645\u0644\u0627\u0621 \u0648\u0627\u0644\u0641\u0627\u0633\u062f\u064a\u0646\u061f",
      "annotationEn": null,
      "idBookSeries": null,
      "seriesNumber": null,
      "ISBNEbook": "",
      "ISBNEbookLocked": "0",
      "ISBNPrinted": "",
      "ISBNMobi": "",
      "idPublisher": "1201",
      "uid": "1ff17461-8b3b-11e7-a367-001d92661257",
      "version": "230",
      "idLanguage": "ar",
      "canBeUsedInMinimart": "1",
      "autoCoverPage": null,
      "autoTitlePage": null,
      "autoCopyrightPage": null,
      "originalTitle": "",
      "publishingYear": "2007",
      "idFilePDFCover": null,
      "idPODOption": "6091",
      "printedIn": "",
      "designMode": "0",
      "ebookPublisher": null,
      "idUserExtSales": "6122",
      "sumItunes": null,
      "sumElib": null,
      "sumApp": null,
      "lastExtSalesMailDate": null,
      "idBookUploadAgent": null,
      "publishDate": "2018-02-27 12:41:58",
      "approveDate": "2018-02-27 12:42:47",
      "translitTitle": "",
      "translitAnnotation": "",
      "addUTMCodes": "0",
      "focusBookDate": null,
      "activityRating": "362",
      "deleted": "0",
      "referencePageCount": null,
      "referencePageCountIgnore": "0",
      "chapterCount": "18",
      "wordCount": "2576",
      "rtl": "1",
      "languageName": "Arabic",
      "idUser": "6122",
      "userLogin": "drnadhim@gmail.com",
      "price": "1.99",
      "VAT": "0.0000",
      "currencyDesignation": "$",
      "priceConverted": "1.990000000",
      "VATConverted": "0.000000000",
      "currencyDesignationConverted": "$",
      "isBought": "0",
      "isFavorite": "0",
      "bwcCurrentPage": null,
      "bwcFontSize": null,
      "isMyBook": "0",
      "extSalesUpdated": "1",
      "adminTitle": "\u0627\u0644\u0639\u0631\u0627\u0642 \u0648\u0627\u0644\u0625\u0635\u0644\u0627\u062d [drnadhim@gmail.com] {5256}",
      "KBHash": null,
      "mobi": "0",
      "epub": "0",
      "fb2": "0",
      "eNovella": "0",
      "PDF": "0",
      "POD": "0",
      "borrowedLibraryThisMonth": null,
      "borrowedUserThisMonth": null,
      "borrowCount": null,
      "haveLeaseInAnotherLibrary": null,
      "isLibraryUser": null,
      "budgetUsed": null,
      "coverFileData": "{\"idFile\":32958,\"ext\":\"jpg\",\"name\":\"\u0627\u0644\u0639\u0631\u0627\u0642 \u0648\u0627\u0644\u0625\u0635\u0644\u0627\u062d\",\"width\":2000,\"height\":2477}",
      "bookAuthorsJSON": null,
      "bookGenresJSON": null,
      "booksAccessJSON": null,
      "images": [
        "32958"
      ],
      "bookAuthors": [
        {
          "caption": "\u0646\u0627\u0638\u0645 \u0645\u062c\u0628\u0644 \u0627\u0644\u0639\u0628\u0627\u062f\u064a",
          "email": "drnadhim@gmail.com",
          "firstName": "\u0646\u0627\u0638\u0645",
          "homePage": "https:\/\/www.linkedin.com\/in\/nadhim-faleh-faleh-21972810a\/",
          "idAuthor": "3844",
          "lastName": "\u0627\u0644\u0639\u0628\u0627\u062f\u064a",
          "middleName": "\u0645\u062c\u0628\u0644",
          "nickname": "\u0646\u0627\u0638\u0645 \u0627\u0644\u0639\u0628\u0627\u062f\u064a"
        }
      ],
      "bookGenres": [
        {
          "fb2Name": "sci_politics",
          "idBook": "5256",
          "idBookGenre": "12397",
          "idGenre": "28",
          "name": "Politics"
        },
        {
          "fb2Name": "religion_rel",
          "idBook": "5256",
          "idBookGenre": "12396",
          "idGenre": "132",
          "name": "Religion"
        },
        {
          "fb2Name": null,
          "idBook": "5256",
          "idBookGenre": "12399",
          "idGenre": "361",
          "name": "\u0627\u0644\u0639\u0627\u0626\u0644\u0629 \u0648\u0627\u0644\u0645\u062c\u062a\u0645\u0639"
        },
        {
          "fb2Name": "sci_history",
          "idBook": "5256",
          "idBookGenre": "12394",
          "idGenre": "390",
          "name": "History"
        },
        {
          "fb2Name": null,
          "idBook": "5256",
          "idBookGenre": "12395",
          "idGenre": "482",
          "name": "History and civilisations"
        },
        {
          "fb2Name": null,
          "idBook": "5256",
          "idBookGenre": "12400",
          "idGenre": "483",
          "name": "Novels and stories"
        },
        {
          "fb2Name": null,
          "idBook": "5256",
          "idBookGenre": "12398",
          "idGenre": "487",
          "name": "Biographies and diaries"
        }
      ],
      "booksAccess": []
    },
    {
      "idBook": "7406",
      "created": "2018-02-23 22:12:54",
      "updated": "2018-02-26 16:08:06",
      "idBookType": "book",
      "idProductsVariations": "8122",
      "title": "\u0627\u0644\u062d\u0636\u0627\u0631\u0629 \u0627\u0644\u0625\u0633\u0644\u0627\u0645\u064a\u0629 \u0648\u0622\u0641\u0627\u0642 \u0627\u0644\u0645\u0633\u062a\u0642\u0628\u0644",
      "titleEn": null,
      "idFileCover": "42899",
      "idFileContent": null,
      "annotation": "\u0643\u062a\u0627\u0628 \u064a\u062a\u0646\u0627\u0648\u0644 \u0627\u0644\u062d\u0636\u0627\u0631\u0629 \u0627\u0644\u0627\u0633\u0644\u0627\u0645\u064a\u0629 \u0628\u0627\u0644\u0628\u062d\u062b \u0648\u0627\u0644\u062f\u0631\u0627\u0633\u0629 \u0648\u062a\u0648\u0635\u0644 \u0627\u0644\u0649 \u0627\u0646 \u0647\u0630\u0647 \u0627\u0644\u062d\u0636\u0627\u0631\u0629 \u0644\u0627\u0632\u0627\u0644\u062a \u062d\u064a\u0629\u0648\u0642\u0627\u062f\u0631\u0629 \u0639\u0644\u0649 \u0627\u0644\u062a\u0641\u0627\u0639\u0644 \u0645\u0639 \u0627\u0644\u062d\u0636\u0627\u0631\u0627\u062a \u0627\u0644\u0627\u062e\u0631\u0649 \u0641\u064a \u0627\u0644\u0639\u0627\u0644\u0645 \u0627\u062e\u0630\u0627 \u0648\u0639\u0637\u0627\u0621 \u060c \u0648\u062a\u0645\u0644\u0643 \u062e\u0635\u0627\u0626\u0635 \u062a\u0633\u0627\u0639\u062f \u0641\u064a \u0627\u0644\u0645\u062d\u0627\u0641\u0638\u0629 \u0639\u0644\u0649 \u0647\u0648\u064a\u0629 \u0627\u0644\u0645\u062c\u062a\u0645\u0639 \u0627\u0644\u0627\u0633\u0644\u0627\u0645\u064a \u0648\u0645\u0646\u0639\u0647 \u0645\u0646 \u0627\u0644\u0627\u0646\u0635\u0647\u0627\u0631 \u0648\u0627\u0644\u0630\u0648\u0628\u0627\u0646 \u0641\u064a \u063a\u064a\u0631\u0647 .\u0645\u0646 \u0627\u0644\u062d\u0636\u0627\u0631\u0627\u062a",
      "annotationEn": null,
      "idBookSeries": null,
      "seriesNumber": null,
      "ISBNEbook": null,
      "ISBNEbookLocked": "0",
      "ISBNPrinted": "",
      "ISBNMobi": null,
      "idPublisher": "1465",
      "uid": "b24116dd-18e6-11e8-a5fe-901b0eed556c",
      "version": "46",
      "idLanguage": "ar",
      "canBeUsedInMinimart": "1",
      "autoCoverPage": null,
      "autoTitlePage": null,
      "autoCopyrightPage": null,
      "originalTitle": "",
      "publishingYear": "2017",
      "idFilePDFCover": null,
      "idPODOption": null,
      "printedIn": null,
      "designMode": "0",
      "ebookPublisher": null,
      "idUserExtSales": "10226",
      "sumItunes": null,
      "sumElib": null,
      "sumApp": null,
      "lastExtSalesMailDate": null,
      "idBookUploadAgent": null,
      "publishDate": "2018-02-26 10:25:38",
      "approveDate": "2018-02-26 16:08:06",
      "translitTitle": null,
      "translitAnnotation": null,
      "addUTMCodes": "0",
      "focusBookDate": null,
      "activityRating": "207",
      "deleted": "0",
      "referencePageCount": null,
      "referencePageCountIgnore": "0",
      "chapterCount": "24",
      "wordCount": "80278",
      "rtl": "1",
      "languageName": "Arabic",
      "idUser": "10226",
      "userLogin": "jihad.baydoun@hotmail.com",
      "price": "8.00",
      "VAT": "0.0000",
      "currencyDesignation": "$",
      "priceConverted": "8.000000000",
      "VATConverted": "0.000000000",
      "currencyDesignationConverted": "$",
      "isBought": "0",
      "isFavorite": "0",
      "bwcCurrentPage": null,
      "bwcFontSize": null,
      "isMyBook": "0",
      "extSalesUpdated": "1",
      "adminTitle": "\u0627\u0644\u062d\u0636\u0627\u0631\u0629 \u0627\u0644\u0625\u0633\u0644\u0627\u0645\u064a\u0629 \u0648\u0622\u0641\u0627\u0642 \u0627\u0644\u0645\u0633\u062a\u0642\u0628\u0644 [jihad.baydoun@hotmail.com] {7406}",
      "KBHash": null,
      "mobi": "0",
      "epub": "0",
      "fb2": "0",
      "eNovella": "0",
      "PDF": "0",
      "POD": "0",
      "borrowedLibraryThisMonth": null,
      "borrowedUserThisMonth": null,
      "borrowCount": null,
      "haveLeaseInAnotherLibrary": null,
      "isLibraryUser": null,
      "budgetUsed": null,
      "coverFileData": "{\"idFile\":42899,\"ext\":\"jpg\",\"name\":\"\u0627\u0644\u062d\u0636\u0627\u0631\u0629 \u0627\u0644\u0625\u0633\u0644\u0627\u0645\u064a\u0629 \u0648\u0622\u0641\u0627\u0642 \u0627\u0644\u0645\u0633\u062a\u0642\u0628\u0644\",\"width\":800,\"height\":1114}",
      "bookAuthorsJSON": null,
      "bookGenresJSON": null,
      "booksAccessJSON": null,
      "images": [
        "42899"
      ],
      "bookAuthors": [
        {
          "caption": "\u0623. \u062f. \u0647\u0627\u0634\u0645  \u064a\u062d\u064a\u0649 \u0627\u0644\u0645\u0644\u0627\u062d",
          "email": null,
          "firstName": "\u0623. \u062f. \u0647\u0627\u0634\u0645",
          "homePage": null,
          "idAuthor": "5721",
          "lastName": "\u064a\u062d\u064a\u0649 \u0627\u0644\u0645\u0644\u0627\u062d",
          "middleName": null,
          "nickname": null
        }
      ],
      "bookGenres": [
        {
          "fb2Name": null,
          "idBook": "7406",
          "idBookGenre": "16540",
          "idGenre": "482",
          "name": "History and civilisations"
        }
      ],
      "booksAccess": []
    },
    {
      "idBook": "7217",
      "created": "2018-02-16 11:58:30",
      "updated": "2018-02-23 19:18:28",
      "idBookType": "book",
      "idProductsVariations": "7933",
      "title": "\u0627\u0644\u0623\u0646\u062f\u0644\u0633 \u0648\u0645\u0627 \u0641\u064a\u0647\u0627 \u0645\u0646 \u0627\u0644\u0628\u0644\u0627\u062f",
      "titleEn": null,
      "idFileCover": "41627",
      "idFileContent": null,
      "annotation": "\u0645\u0639\u062c\u0645 \u0635\u063a\u064a\u0631 \u064a\u0639\u0631\u0641 \u0628\u0627\u0644\u0623\u0646\u062f\u0644\u0633 \u0648\u064a\u0630\u0643\u0631 \u0623\u0634\u0647\u0631 \u0645\u0627\u0641\u064a\u0647\u0627 \u0645\u0646 \u0645\u062f\u0646 \u0648\u0623\u0646\u0647\u0627\u0631 \u0648\u0642\u0631\u0649 \u0645\u0639 \u0645\u0631\u0627\u0639\u0627\u0629 \u0627\u0644\u0636\u0628\u0637 \u0627\u0644\u0644\u063a\u0648\u064a \u0627\u0644\u062a\u0627\u0645 \u0644\u0643\u0644 \u0627\u0633\u0645 \u0645\u0646 \u0623\u0633\u0645\u0627\u0626\u0647\u0627 \u0648\u0642\u062f \u0630\u0643\u0631 \u0623\u0645\u0627\u0643\u0646 \u0627\u0644\u0623\u0646\u0647\u0627\u0631 \u0648\u0630\u0643\u0631 \u0645\u064a\u0632\u0627\u062a\u0647\u0627 \u0648\u0645\u064a\u0632\u0627\u062a \u0627\u0644\u0645\u062f\u0646",
      "annotationEn": null,
      "idBookSeries": null,
      "seriesNumber": null,
      "ISBNEbook": null,
      "ISBNEbookLocked": "0",
      "ISBNPrinted": "",
      "ISBNMobi": null,
      "idPublisher": "1465",
      "uid": "b4d2d170-1310-11e8-a5fe-901b0eed556c",
      "version": "18",
      "idLanguage": "ar",
      "canBeUsedInMinimart": "1",
      "autoCoverPage": null,
      "autoTitlePage": null,
      "autoCopyrightPage": null,
      "originalTitle": "",
      "publishingYear": "2015",
      "idFilePDFCover": null,
      "idPODOption": null,
      "printedIn": null,
      "designMode": "0",
      "ebookPublisher": null,
      "idUserExtSales": "10226",
      "sumItunes": null,
      "sumElib": null,
      "sumApp": null,
      "lastExtSalesMailDate": null,
      "idBookUploadAgent": null,
      "publishDate": "2018-02-23 16:01:21",
      "approveDate": "2018-02-23 19:18:28",
      "translitTitle": null,
      "translitAnnotation": null,
      "addUTMCodes": "0",
      "focusBookDate": null,
      "activityRating": "209",
      "deleted": "0",
      "referencePageCount": null,
      "referencePageCountIgnore": "0",
      "chapterCount": "9",
      "wordCount": "5061",
      "rtl": "1",
      "languageName": "Arabic",
      "idUser": "10226",
      "userLogin": "jihad.baydoun@hotmail.com",
      "price": "3.00",
      "VAT": "0.0000",
      "currencyDesignation": "$",
      "priceConverted": "3.000000000",
      "VATConverted": "0.000000000",
      "currencyDesignationConverted": "$",
      "isBought": "0",
      "isFavorite": "0",
      "bwcCurrentPage": null,
      "bwcFontSize": null,
      "isMyBook": "0",
      "extSalesUpdated": "1",
      "adminTitle": "\u0627\u0644\u0623\u0646\u062f\u0644\u0633 \u0648\u0645\u0627 \u0641\u064a\u0647\u0627 \u0645\u0646 \u0627\u0644\u0628\u0644\u0627\u062f [jihad.baydoun@hotmail.com] {7217}",
      "KBHash": null,
      "mobi": "0",
      "epub": "0",
      "fb2": "0",
      "eNovella": "0",
      "PDF": "0",
      "POD": "0",
      "borrowedLibraryThisMonth": null,
      "borrowedUserThisMonth": null,
      "borrowCount": null,
      "haveLeaseInAnotherLibrary": null,
      "isLibraryUser": null,
      "budgetUsed": null,
      "coverFileData": "{\"idFile\":41627,\"ext\":\"jpg\",\"name\":\"\u0627\u0644\u0623\u0646\u062f\u0644\u0633 \u0648\u0645\u0627 \u0641\u064a\u0647\u0627 \u0645\u0646 \u0627\u0644\u0628\u0644\u0627\u062f\",\"width\":800,\"height\":1143}",
      "bookAuthorsJSON": null,
      "bookGenresJSON": null,
      "booksAccessJSON": null,
      "images": [
        "41627"
      ],
      "bookAuthors": [
        {
          "caption": "\u0645\u0624\u0644\u0641  \u0645\u062c\u0647\u0648\u0644",
          "email": null,
          "firstName": "\u0645\u0624\u0644\u0641",
          "homePage": null,
          "idAuthor": "5556",
          "lastName": "\u0645\u062c\u0647\u0648\u0644",
          "middleName": null,
          "nickname": null
        }
      ],
      "bookGenres": [
        {
          "fb2Name": null,
          "idBook": "7217",
          "idBookGenre": "16257",
          "idGenre": "482",
          "name": "History and civilisations"
        },
        {
          "fb2Name": null,
          "idBook": "7217",
          "idBookGenre": "16258",
          "idGenre": "489",
          "name": "Other"
        }
      ],
      "booksAccess": []
    },
    {
      "idBook": "7349",
      "created": "2018-02-20 14:33:32",
      "updated": "2018-02-23 10:24:08",
      "idBookType": "book",
      "idProductsVariations": "8065",
      "title": "\u0623\u062f\u0628 \u0627\u0644\u0648\u0641\u0627\u062f\u0629 \u0644\u062f\u0649 \u0623\u062f\u0628\u0627\u0621 \u0627\u0644\u0623\u0646\u062f\u0644\u0633  \u062f\u0627\u062e\u0644 \u0648\u062e\u0627\u0631\u062c \u0627\u0644\u0623\u0646\u062f\u0644\u0633",
      "titleEn": null,
      "idFileCover": "42666",
      "idFileContent": null,
      "annotation": "\u0641\u0642\u062f \u0634\u063a\u0644 \u0627\u0644\u0634\u0639\u0631 \u0627\u0644\u0639\u0631\u0628\u064a \u0641\u064a \u0627\u0644\u0623\u0646\u062f\u0644\u0633 \u0627\u0644\u0628\u0627\u062d\u062b\u064a\u0646 \u0648\u0627\u0644\u062f\u0627\u0631\u0633\u064a\u0646 \u0641\u064a \u0627\u0644\u0639\u0635\u0631 \u0627\u0644\u062d\u062f\u064a\u062b\u060c \u0648\u062a\u0646\u0627\u0648\u0644\u0648\u0647 \u0645\u0646 \u062c\u0648\u0627\u0646\u0628 \u0634\u062a\u0649 \u0641\u062f\u0631\u0633\u0648\u0627 \u0627\u0644\u0634\u0639\u0631\u0627\u0621 \u0648\u0627\u0644\u0643\u062a\u0627\u0628 \u0648\u0627\u0644\u0638\u0648\u0627\u0647\u0631 \u0627\u0644\u0623\u062f\u0628\u064a\u0629 \u0648\u0627\u0644\u0641\u0646\u064a\u0629 \u0641\u064a \u0645\u062c\u0627\u0645\u064a\u0639\u0647\u0645 \u0627\u0644\u0634\u0639\u0631\u064a\u0629 \u0648\u0627\u0644\u0623\u062f\u0628\u064a\u0629 \u0625\u0644\u0627 \u0623\u0646 \u062f\u0631\u0627\u0633\u0627\u062a\u0647\u0645 \u062a\u0644\u0643 \u0644\u0645 \u062a\u062a\u0637\u0631\u0642 \u0625\u0644\u0649 \u0647\u0630\u0647 \u0627\u0644\u0638\u0627\u0647\u0631\u0629 \u0628\u0627\u0633\u062a\u062b\u0646\u0627\u0621 \u0627\u0644\u062f\u0643\u062a\u0648\u0631 \u0625\u062d\u0633\u0627\u0646 \u0639\u0628\u0627\u0633 \u0641\u0642\u062f \u0623\u0634\u0627\u0631 \u0625\u0644\u064a\u0647\u0627 \u0641\u064a \u0643\u062a\u0627\u0628\u0647 \u062a\u0627\u0631\u064a\u062e \u0627\u0644\u0623\u062f\u0628 \u0627\u0644\u0623\u0646\u062f\u0644\u0633\u064a (\u0639\u0635\u0631 \u0633\u064a\u0627\u062f\u0629 \u0642\u0631\u0637\u0628\u0629) \u0625\u0634\u0627\u0631\u0629 \u062e\u0641\u064a\u0641\u0629 \u0644\u0627 \u062a\u062a\u062c\u0627\u0648\u0632 \u0628\u0636\u0639\u0629 \u0627\u0633\u0637\u0631\u060c \u0648\u0644\u0643\u0646 \u0643\u0627\u0646 \u0644\u0647\u0627 \u0627\u0644\u0641\u0636\u0644 \u0641\u064a \u0627\u0644\u0627\u0647\u062a\u062f\u0627\u0621 \u0644\u062f\u0631\u0627\u0633\u0629 \u0627\u0644\u0645\u0648\u0636\u0648\u0639\u060c \u0648\u0639\u0646\u062f \u0627\u0644\u0628\u062d\u062b \u0639\u0646\u0647 \u0641\u064a \u0646\u062a\u0627\u062c \u0627\u0644\u0623\u062f\u0628\u0627\u0621 \u0627\u0644\u0623\u0646\u062f\u0644\u0633\u064a\u064a\u0646 \u062a\u0628\u064a\u0646 \u0644\u064a \u0628\u0623\u0646\u0647 \u062a\u0631\u0643 \u0623\u062b\u0631\u0627 \u0648\u0627\u0636\u062d\u0627 \u0641\u064a \u0627\u0644\u0634\u0639\u0631 \u0627\u0644\u0623\u0646\u062f\u0644\u0633\u064a\u060c \u0648\u0644\u0645 \u064a\u062d\u0638 \u0628\u0639\u0646\u0627\u064a\u0629 \u0627\u0644\u062f\u0627\u0631\u0633\u064a\u0646\u060c \u0641\u0648\u062c\u062a \u0644\u0632\u0627\u0645\u0627 \u0639\u0644\u064a \u0623\u0646 \u0623\u0639\u0645\u062f \u0625\u0644\u0649 \u062f\u0631\u0627\u0633\u062a\u0647 \u062f\u0631\u0627\u0633\u0629 \u0648\u0627\u0642\u0639\u064a\u0629 \u0645\u0646 \u0634\u0623\u0646\u0647\u0627 \u0623\u0646 \u062a\u062b\u0631\u064a \u0627\u0644\u0645\u0643\u062a\u0628\u0629 \u0627\u0644\u0623\u062f\u0628\u064a\u0629\u060c \u0648\u0623\u0646 \u062a\u0643\u0648\u0646 \u062d\u0644\u0642\u0629 \u0648\u0635\u0644 \u0641\u064a \u0633\u0644\u0633\u0644\u0629 \u0627\u0644\u0628\u062d\u0648\u062b \u0627\u0644\u062a\u064a \u062a\u0646\u0627\u0648\u0644\u062a \u0627\u0644\u0623\u062f\u0628 \u0627\u0644\u0639\u0631\u0628\u064a \u0641\u064a \u0627\u0644\u0623\u0646\u062f\u0644\u0633.\r\n\u0648\u0627\u0639\u062a\u0645\u062f\u062a \u0641\u064a \u062f\u0631\u0627\u0633\u062a\u064a \u0639\u0644\u0649 \u0627\u0644\u0645\u0635\u0627\u062f\u0631 \u0627\u0644\u062a\u064a \u062c\u0645\u0639\u062a \u0623\u0634\u0639\u0627\u0631 \u0627\u0644\u0639\u0631\u0628 \u0641\u064a \u0627\u0644\u0623\u0646\u062f\u0644\u0633\u060c \u0648\u0645\u0646 \u0623\u0628\u0631\u0632 \u0627\u0644\u0645\u0635\u0627\u062f\u0631 \u0627\u0644\u062a\u064a \u0627\u0639\u062a\u0645\u062f\u062a \u0639\u0644\u064a\u0647\u0627: \u0646\u0641\u062d \u0627\u0644\u0637\u064a\u0628 \u0644\u0644\u0645\u0642\u0631\u064a\u060c \u0648\u0627\u0644\u0625\u062d\u0627\u0637\u0629 \u0641\u064a \u0623\u062e\u0628\u0627\u0631 \u063a\u0631\u0646\u0627\u0637\u0629 \u0644\u0648\u0632\u064a\u0631 \u0627\u0644\u0623\u0646\u062f\u0644\u0633 \u0644\u0633\u0627\u0646 \u0627\u0644\u062f\u064a\u0646 \u0628\u0646 \u0627\u0644\u062e\u0637\u064a\u0628\u060c \u0648\u0627\u0644\u0639\u0642\u062f \u0627\u0644\u0641\u0631\u064a\u062f \u0644\u0627\u0628\u0646 \u0639\u0628\u062f \u0631\u0628\u0647 \u0627\u0644\u0623\u0646\u062f\u0644\u0633\u064a\u060c \u0648\u0627\u0644\u0630\u062e\u064a\u0631\u0629 \u0641\u064a \u0645\u062d\u0627\u0633\u0646 \u0623\u0647\u0644 \u0627\u0644\u062c\u0632\u064a\u0631\u0629 \u0644\u0627\u0628\u0646 \u0628\u0633\u0627\u0645 \u0627\u0644\u0634\u0646\u062a\u0631\u064a\u0646\u064a\u060c \u0648\u062a\u0627\u0631\u064a\u062e \u0627\u0628\u0646 \u062e\u0644\u062f\u0648\u0646\u060c \u0648\u063a\u064a\u0631\u0647\u0627.\r\n",
      "annotationEn": null,
      "idBookSeries": null,
      "seriesNumber": null,
      "ISBNEbook": null,
      "ISBNEbookLocked": "0",
      "ISBNPrinted": "",
      "ISBNMobi": null,
      "idPublisher": "1465",
      "uid": "06af14b7-164b-11e8-a5fe-901b0eed556c",
      "version": "25",
      "idLanguage": "ar",
      "canBeUsedInMinimart": "1",
      "autoCoverPage": null,
      "autoTitlePage": null,
      "autoCopyrightPage": null,
      "originalTitle": "",
      "publishingYear": "2018",
      "idFilePDFCover": null,
      "idPODOption": null,
      "printedIn": null,
      "designMode": "0",
      "ebookPublisher": null,
      "idUserExtSales": "10226",
      "sumItunes": null,
      "sumElib": null,
      "sumApp": null,
      "lastExtSalesMailDate": null,
      "idBookUploadAgent": null,
      "publishDate": "2018-02-23 08:25:13",
      "approveDate": "2018-02-23 10:24:08",
      "translitTitle": null,
      "translitAnnotation": null,
      "addUTMCodes": "0",
      "focusBookDate": null,
      "activityRating": "290",
      "deleted": "0",
      "referencePageCount": null,
      "referencePageCountIgnore": "0",
      "chapterCount": "13",
      "wordCount": "63613",
      "rtl": "1",
      "languageName": "Arabic",
      "idUser": "10226",
      "userLogin": "jihad.baydoun@hotmail.com",
      "price": "6.00",
      "VAT": "0.0000",
      "currencyDesignation": "$",
      "priceConverted": "6.000000000",
      "VATConverted": "0.000000000",
      "currencyDesignationConverted": "$",
      "isBought": "0",
      "isFavorite": "0",
      "bwcCurrentPage": null,
      "bwcFontSize": null,
      "isMyBook": "0",
      "extSalesUpdated": "1",
      "adminTitle": "\u0623\u062f\u0628 \u0627\u0644\u0648\u0641\u0627\u062f\u0629 \u0644\u062f\u0649 \u0623\u062f\u0628\u0627\u0621 \u0627\u0644\u0623\u0646\u062f\u0644\u0633  \u062f\u0627\u062e\u0644 \u0648\u062e\u0627\u0631\u062c \u0627\u0644\u0623\u0646\u062f\u0644\u0633 [jihad.baydoun@hotmail.com] {7349}",
      "KBHash": null,
      "mobi": "0",
      "epub": "0",
      "fb2": "0",
      "eNovella": "0",
      "PDF": "0",
      "POD": "0",
      "borrowedLibraryThisMonth": null,
      "borrowedUserThisMonth": null,
      "borrowCount": null,
      "haveLeaseInAnotherLibrary": null,
      "isLibraryUser": null,
      "budgetUsed": null,
      "coverFileData": "{\"idFile\":42666,\"ext\":\"jpg\",\"name\":\"\u0623\u062f\u0628 \u0627\u0644\u0648\u0641\u0627\u062f\u0629 \u0644\u062f\u0649 \u0623\u062f\u0628\u0627\u0621 \u0627\u0644\u0623\u0646\u062f\u0644\u0633  \u062f\u0627\u062e\u0644 \u0648\u062e\u0627\u0631\u062c \u0627\u0644\u0623\u0646\u062f\u0644\u0633\",\"width\":800,\"height\":1204}",
      "bookAuthorsJSON": null,
      "bookGenresJSON": null,
      "booksAccessJSON": null,
      "images": [
        "42666"
      ],
      "bookAuthors": [
        {
          "caption": "\u064a\u0648\u0633\u0641 \u0625\u0628\u0631\u0627\u0647\u064a\u0645  \u0642\u0637\u0631\u064a\u0628",
          "email": null,
          "firstName": "\u064a\u0648\u0633\u0641 \u0625\u0628\u0631\u0627\u0647\u064a\u0645",
          "homePage": null,
          "idAuthor": "5668",
          "lastName": "\u0642\u0637\u0631\u064a\u0628",
          "middleName": null,
          "nickname": null
        }
      ],
      "bookGenres": [
        {
          "fb2Name": null,
          "idBook": "7349",
          "idBookGenre": "16432",
          "idGenre": "482",
          "name": "History and civilisations"
        },
        {
          "fb2Name": null,
          "idBook": "7349",
          "idBookGenre": "16431",
          "idGenre": "488",
          "name": "\u0627\u0644\u0623\u062f\u0628 \u0648\u0627\u0644\u0634\u0639\u0631"
        }
      ],
      "booksAccess": []
    }
  ],
  "token": null,
  "errorCode": null,
  "errorMessage": null
}